ximilar_client_new-1.21.8-py3.10-nspkg.pth
tests/__init__.py
tests/client.py
tests/conftest.py
ximilar/client/__init__.py
ximilar/client/asyncr.py
ximilar/client/client.py
ximilar/client/colors.py
ximilar/client/constants.py
ximilar/client/custom.py
ximilar/client/detection.py
ximilar/client/exceptions.py
ximilar/client/face.py
ximilar/client/flows.py
ximilar/client/ocr.py
ximilar/client/recognition.py
ximilar/client/removebg.py
ximilar/client/search.py
ximilar/client/similarity.py
ximilar/client/tagging.py
ximilar/client/upscaler.py
ximilar/client/utils/__init__.py
ximilar/client/utils/decorators.py
ximilar/client/utils/json_data.py
ximilar_client_new-1.21.8.dist-info/LICENSE
ximilar_client_new-1.21.8.dist-info/METADATA
ximilar_client_new-1.21.8.dist-info/WHEEL
ximilar_client_new-1.21.8.dist-info/namespace_packages.txt
ximilar_client_new-1.21.8.dist-info/top_level.txt
ximilar_client_new-1.21.8.dist-info/RECORD
