Metadata-Version: 2.1
Name: ximilar-client-new
Version: 1.21.8
Summary: The Ximilar App and Vize.ai Client.
Home-page: https://gitlab.com/ximilar-public/ximilar-vize-api
Author: Michal Lukac, David Novak and Ximilar.com Team
Author-email: tech@ximilar.com
License: Apache 2.0
Keywords: machine learning,multimedia,json,rest,data
Classifier: Development Status :: 3 - Alpha
Classifier: Programming Language :: Python :: 3.4
Classifier: Topic :: Scientific/Engineering :: Artificial Intelligence
License-File: LICENSE
Requires-Dist: requests (==2.31.0)
Requires-Dist: opencv-contrib-python-headless (==4.8.0.74)
Requires-Dist: pytest (>=3.0.3)
Requires-Dist: tqdm (==4.65.0)
